poetrip/__init__.py
poetrip/cli.py
poetrip/pipfile.py
poetrip/pyproject.py
poetrip-1.0.0.dist-info/entry_points.txt
poetrip-1.0.0.dist-info/LICENSE
poetrip-1.0.0.dist-info/WHEEL
poetrip-1.0.0.dist-info/METADATA
poetrip-1.0.0.dist-info/RECORD
